aprscot/__init__.py
aprscot/classes.py
aprscot/commands.py
aprscot/constants.py
aprscot/functions.py
aprscot-6.1.0.dist-info/LICENSE
aprscot-6.1.0.dist-info/METADATA
aprscot-6.1.0.dist-info/WHEEL
aprscot-6.1.0.dist-info/entry_points.txt
aprscot-6.1.0.dist-info/top_level.txt
aprscot-6.1.0.dist-info/RECORD
