Metadata-Version: 2.1
Name: aprscot
Version: 6.1.0
Summary: APRS Cursor-on-Target Gateway.
Home-page: https://github.com/ampledata/aprscot
Author: Greg Albrecht
Author-email: oss@undef.net
License: Apache License, Version 2.0
Keywords: Ham Radio,APRS,Cursor on Target,ATAK,TAK,CoT
Classifier: Topic :: Communications :: Ham Radio
Classifier: Programming Language :: Python
Classifier: License :: OSI Approved :: Apache Software License
License-File: LICENSE
Requires-Dist: aprslib
Requires-Dist: pytak (>=5.4.0)
